projectclone/__init__.py
projectclone/backup.py
projectclone/banner.py
projectclone/cas_engine.py
projectclone/checkout_engine.py
projectclone/cleanup.py
projectclone/cli.py
projectclone/diff_engine.py
projectclone/gc_engine.py
projectclone/integrity_engine.py
projectclone/list_engine.py
projectclone/rotation.py
projectclone/scanner.py
projectclone/status_engine.py
projectclone/sync_engine.py
projectclone/utils.py
projectclone/verify_engine.py
projectclone-4.0.1.dist-info/METADATA
projectclone-4.0.1.dist-info/WHEEL
projectclone-4.0.1.dist-info/entry_points.txt
projectclone-4.0.1.dist-info/top_level.txt
projectclone-4.0.1.dist-info/RECORD
