Metadata-Version: 2.4
Name: projectclone
Version: 4.0.1
Summary: Create exact, self-contained, reproducible project snapshots including git, caches, configs, and environment artifacts.
Author-email: Dhruv <dhruv13x@gmail.com>
Maintainer-email: Dhruv <dhruv13x@gmail.com>
License: MIT
Project-URL: Homepage, https://github.com/dhruv13x/projectclone
Project-URL: Repository, https://github.com/dhruv13x/projectclone.git
Project-URL: Issues, https://github.com/dhruv13x/projectclone/issues
Keywords: backup,snapshot,clone,filesystem,archive,project-clone,self-contained-env,developer-tools
Classifier: Development Status :: 4 - Beta
Classifier: Environment :: Console
Classifier: Intended Audience :: Developers
Classifier: Topic :: System :: Archiving :: Backup
Classifier: Topic :: Software Development :: Build Tools
Classifier: License :: OSI Approved :: MIT License
Classifier: Operating System :: OS Independent
Classifier: Programming Language :: Python :: 3
Classifier: Programming Language :: Python :: 3 :: Only
Requires-Python: >=3.8
Requires-Dist: rich>=13.0
Requires-Dist: tqdm>=4.66
Provides-Extra: dev
Requires-Dist: pytest>=8.0; extra == "dev"
Requires-Dist: pytest-cov>=5.0; extra == "dev"
Requires-Dist: black>=24.0; extra == "dev"
Requires-Dist: mypy>=1.10; extra == "dev"
Requires-Dist: ruff>=0.4.0; extra == "dev"
